tuhls/__init__.py
tuhls/core/__init__.py
tuhls/core/admin.py
tuhls/core/admin_urls.py
tuhls/core/apps.py
tuhls/core/auth.py
tuhls/core/fields.py
tuhls/core/forms.py
tuhls/core/manage.py
tuhls/core/models.py
tuhls/core/serializers.py
tuhls/core/settings.py
tuhls/core/utils.py
tuhls/core/validators.py
tuhls/core/widgets.py
tuhls/core/country_flags/.gitignore
tuhls/core/country_flags/README.md
tuhls/core/country_flags/countries.json
tuhls/core/country_flags/package.json
tuhls/core/country_flags/png1000px/ad.png
tuhls/core/country_flags/png1000px/ae.png
tuhls/core/country_flags/png1000px/af.png
tuhls/core/country_flags/png1000px/ag.png
tuhls/core/country_flags/png1000px/ai.png
tuhls/core/country_flags/png1000px/al.png
tuhls/core/country_flags/png1000px/am.png
tuhls/core/country_flags/png1000px/ao.png
tuhls/core/country_flags/png1000px/aq.png
tuhls/core/country_flags/png1000px/ar.png
tuhls/core/country_flags/png1000px/as.png
tuhls/core/country_flags/png1000px/at.png
tuhls/core/country_flags/png1000px/au.png
tuhls/core/country_flags/png1000px/aw.png
tuhls/core/country_flags/png1000px/ax.png
tuhls/core/country_flags/png1000px/az.png
tuhls/core/country_flags/png1000px/ba.png
tuhls/core/country_flags/png1000px/bb.png
tuhls/core/country_flags/png1000px/bd.png
tuhls/core/country_flags/png1000px/be.png
tuhls/core/country_flags/png1000px/bf.png
tuhls/core/country_flags/png1000px/bg.png
tuhls/core/country_flags/png1000px/bh.png
tuhls/core/country_flags/png1000px/bi.png
tuhls/core/country_flags/png1000px/bj.png
tuhls/core/country_flags/png1000px/bl.png
tuhls/core/country_flags/png1000px/bm.png
tuhls/core/country_flags/png1000px/bn.png
tuhls/core/country_flags/png1000px/bo.png
tuhls/core/country_flags/png1000px/bq.png
tuhls/core/country_flags/png1000px/br.png
tuhls/core/country_flags/png1000px/bs.png
tuhls/core/country_flags/png1000px/bt.png
tuhls/core/country_flags/png1000px/bv.png
tuhls/core/country_flags/png1000px/bw.png
tuhls/core/country_flags/png1000px/by.png
tuhls_core-1.1.9.dist-info/LICENSE
tuhls_core-1.1.9.dist-info/WHEEL
tuhls_core-1.1.9.dist-info/METADATA
tuhls_core-1.1.9.dist-info/RECORD
